datalab_python/__init__.py
datalab_python/info.py
datalab_python-0.1.1.dist-info/METADATA
datalab_python-0.1.1.dist-info/WHEEL
datalab_python-0.1.1.dist-info/top_level.txt
datalab_python-0.1.1.dist-info/RECORD
