Metadata-Version: 2.1
Name: datalab-python
Version: 0.1.1
Summary: The DataLab python client
Home-page: https://bigdatalab.ai
Author: DataLab Team
Author-email: p.korovess@bidatalab.ai
License: UNKNOWN
Platform: UNKNOWN
Classifier: Programming Language :: Python :: 3
Classifier: License :: OSI Approved :: MIT License
Classifier: Operating System :: OS Independent
Requires-Python: >=3.6
Provides-Extra: dev
Requires-Dist: black>=21.0; extra == "dev"
Requires-Dist: flake8>=3.9; extra == "dev"
Requires-Dist: isort>=5.0; extra == "dev"
Requires-Dist: pytest-cov>=2.0; extra == "dev"
Requires-Dist: pytest>=6.0; extra == "dev"
